ms_map.cpython-37m-darwin.so
ms_map-1.1.1.dist-info/LICENSE
ms_map-1.1.1.dist-info/METADATA
ms_map-1.1.1.dist-info/WHEEL
ms_map-1.1.1.dist-info/top_level.txt
ms_map-1.1.1.dist-info/RECORD
