Metadata-Version: 2.1
Name: ms-map
Version: 1.1.1
Summary: A datastructure for efficient storage of mass spectrometry data
Home-page: https://github.com/zmcgrath96/ms_map
Author: Zachary McGrath
Author-email: zmcgrath96@gmail.com
License: UNKNOWN
Keywords: bioinformtatics mass_spectrometry ms map
Platform: UNKNOWN
